zabbix_enums/__init__.py
zabbix_enums/latest/__init__.py
zabbix_enums/latest/action.py
zabbix_enums/latest/alert.py
zabbix_enums/latest/auditlog.py
zabbix_enums/latest/authentication.py
zabbix_enums/latest/autoregistration.py
zabbix_enums/latest/connector.py
zabbix_enums/latest/correlation.py
zabbix_enums/latest/dashboard.py
zabbix_enums/latest/dcheck.py
zabbix_enums/latest/dhost.py
zabbix_enums/latest/discoveryrule.py
zabbix_enums/latest/discoveryruleprototype.py
zabbix_enums/latest/drule.py
zabbix_enums/latest/dservice.py
zabbix_enums/latest/event.py
zabbix_enums/latest/graph.py
zabbix_enums/latest/graphitem.py
zabbix_enums/latest/graphprototype.py
zabbix_enums/latest/hanode.py
zabbix_enums/latest/host.py
zabbix_enums/latest/hostgroup.py
zabbix_enums/latest/hostinterface.py
zabbix_enums/latest/hostprototype.py
zabbix_enums/latest/housekeeping.py
zabbix_enums/latest/httptest.py
zabbix_enums/latest/image.py
zabbix_enums/latest/item.py
zabbix_enums/latest/itemprototype.py
zabbix_enums/latest/maintenance.py
zabbix_enums/latest/map.py
zabbix_enums/latest/mediatype.py
zabbix_enums/latest/mfa.py
zabbix_enums/latest/module.py
zabbix_enums/latest/problem.py
zabbix_enums/latest/proxy.py
zabbix_enums/latest/proxygroup.py
zabbix_enums/latest/regexp.py
zabbix_enums/latest/report.py
zabbix_enums/latest/role.py
zabbix_enums/latest/script.py
zabbix_enums/latest/service.py
zabbix_enums/latest/settings.py
zabbix_enums/latest/sla.py
zabbix_enums/latest/task.py
zabbix_enums/latest/templatedashboard.py
zabbix_enums/latest/token.py
zabbix_enums/latest/trigger.py
zabbix_enums/latest/triggerprototype.py
zabbix_enums/latest/user.py
zabbix_enums/latest/userdirectory.py
zabbix_enums/latest/usergroup.py
zabbix_enums/latest/usermacro.py
zabbix_enums/latest/valuemap.py
zabbix_enums/latest_lts/__init__.py
zabbix_enums/latest_lts/action.py
zabbix_enums/latest_lts/alert.py
zabbix_enums/latest_lts/auditlog.py
zabbix_enums/latest_lts/authentication.py
zabbix_enums/latest_lts/autoregistration.py
zabbix_enums-1.74.0.dist-info/licenses/LICENSE
zabbix_enums-1.74.0.dist-info/METADATA
zabbix_enums-1.74.0.dist-info/WHEEL
zabbix_enums-1.74.0.dist-info/top_level.txt
zabbix_enums-1.74.0.dist-info/RECORD
