Metadata-Version: 2.4
Name: zabbix-enums
Version: 1.74.0
Summary: An Enum collection for Zabbix API scripting
Home-page: https://github.com/szuro/zabbix-enums
Author: Robert Szulist
Author-email: r.szulist@gmail.com
Project-URL: Bug Tracker, https://github.com/szuro/zabbix-enums/issues
Classifier: Programming Language :: Python :: 3
Classifier: License :: OSI Approved :: MIT License
Classifier: Operating System :: OS Independent
Requires-Python: >=3.9
License-File: LICENSE
Dynamic: license-file
